space/__init__.py
space_python_sdk-0.1.0.dist-info/WHEEL
space_python_sdk-0.1.0.dist-info/METADATA
space_python_sdk-0.1.0.dist-info/RECORD
