Metadata-Version: 2.1
Name: space-python-sdk
Version: 0.1.0
Summary: 
Author: Abbas Jafari
Author-email: a.jafari@zurich.ch
Requires-Python: >=3.8,<4.0
Classifier: Programming Language :: Python :: 3
Classifier: Programming Language :: Python :: 3.10
Classifier: Programming Language :: Python :: 3.8
Classifier: Programming Language :: Python :: 3.9
Requires-Dist: twine (>=3.6.0,<4.0.0)
